[
{"source": "RAVOS Containerdienst", "title": "Bauschutt 3 m³", "type": "Bauschutt", "city": "Köln", "size": "3", "price": "269,00", "lid_price": null, "arrival_price": "inklusive", "departure_price": "inklusive", "max_rental_period": "14", "fee_after_max": "5,95", "cancellation_fee": "Zone 1: 120€, Zone 2: 145€, Zone 3: 205€, Zone 4: 240€", "URL": "https://ravos.de/produkt/container-bauschutt/"},
{"source": "RAVOS Containerdienst", "title": "Bauschutt 5 m³", "type": "Bauschutt", "city": "Köln", "size": "5", "price": "369,00", "lid_price": null, "arrival_price": "inklusive", "departure_price": "inklusive", "max_rental_period": "14", "fee_after_max": "5,95", "cancellation_fee": "Zone 1: 120€, Zone 2: 145€, Zone 3: 205€, Zone 4: 240€", "URL": "https://ravos.de/produkt/container-bauschutt/"},
{"source": "RAVOS Containerdienst", "title": "Bauschutt 7 m³", "type": "Bauschutt", "city": "Köln", "size": "7", "price": "429,00", "lid_price": null, "arrival_price": "inklusive", "departure_price": "inklusive", "max_rental_period": "14", "fee_after_max": "5,95", "cancellation_fee": "Zone 1: 120€, Zone 2: 145€, Zone 3: 205€, Zone 4: 240€", "URL": "https://ravos.de/produkt/container-bauschutt/"},
{"source": "RAVOS Containerdienst", "title": "Baumischabfall 3 m³", "type": "Baumischabfall", "city": "Köln", "size": "3", "price": "449,00", "lid_price": null, "arrival_price": "inklusive", "departure_price": "inklusive", "max_rental_period": "14", "fee_after_max": "5,95", "cancellation_fee": "Zone 1: 120€, Zone 2: 145€, Zone 3: 205€, Zone 4: 240€", "URL": "https://ravos.de/produkt/container-baumischabfall/"},
{"source": "RAVOS Containerdienst", "title": "Baumischabfall 5 m³", "type": "Baumischabfall", "city": "Köln", "size": "5", "price": "549,00", "lid_price": null, "arrival_price": "inklusive", "departure_price": "inklusive", "max_rental_period": "14", "fee_after_max": "5,95", "cancellation_fee": "Zone 1: 120€, Zone 2: 145€, Zone 3: 205€, Zone 4: 240€", "URL": "https://ravos.de/produkt/container-baumischabfall/"},
{"source": "RAVOS Containerdienst", "title": "Baumischabfall 7 m³", "type": "Baumischabfall", "city": "Köln", "size": "7", "price": "629,00", "lid_price": null, "arrival_price": "inklusive", "departure_price": "inklusive", "max_rental_period": "14", "fee_after_max": "5,95", "cancellation_fee": "Zone 1: 120€, Zone 2: 145€, Zone 3: 205€, Zone 4: 240€", "URL": "https://ravos.de/produkt/container-baumischabfall/"},
{"source": "RAVOS Containerdienst", "title": "Baumischabfall 10 m³", "type": "Baumischabfall", "city": "Köln", "size": "10", "price": "849,00", "lid_price": null, "arrival_price": "inklusive", "departure_price": "inklusive", "max_rental_period": "14", "fee_after_max": "5,95", "cancellation_fee": "Zone 1: 120€, Zone 2: 145€, Zone 3: 205€, Zone 4: 240€", "URL": "https://ravos.de/produkt/container-baumischabfall/"},
{"source": "RAVOS Containerdienst", "title": "Gartenabfälle 3 m³", "type": "Gartenabfälle", "city": "Köln", "size": "3", "price": "199,00", "lid_price": null, "arrival_price": "inklusive", "departure_price": "inklusive", "max_rental_period": "14", "fee_after_max": "5,95", "cancellation_fee": "Zone 1: 120€, Zone 2: 145€, Zone 3: 205€, Zone 4: 240€", "URL": "https://ravos.de/produkt/container-gruenschnitt/"},
{"source": "RAVOS Containerdienst", "title": "Gartenabfälle 5 m³", "type": "Gartenabfälle", "city": "Köln", "size": "5", "price": "299,00", "lid_price": null, "arrival_price": "inklusive", "departure_price": "inklusive", "max_rental_period": "14", "fee_after_max": "5,95", "cancellation_fee": "Zone 1: 120€, Zone 2: 145€, Zone 3: 205€, Zone 4: 240€", "URL": "https://ravos.de/produkt/container-gruenschnitt/"},
{"source": "RAVOS Containerdienst", "title": "Gartenabfälle 7 m³", "type": "Gartenabfälle", "city": "Köln", "size": "7", "price": "369,00", "lid_price": null, "arrival_price": "inklusive", "departure_price": "inklusive", "max_rental_period": "14", "fee_after_max": "5,95", "cancellation_fee": "Zone 1: 120€, Zone 2: 145€, Zone 3: 205€, Zone 4: 240€", "URL": "https://ravos.de/produkt/container-gruenschnitt/"},
{"source": "RAVOS Containerdienst", "title": "Gartenabfälle 10 m³", "type": "Gartenabfälle", "city": "Köln", "size": "10", "price": "429,00", "lid_price": null, "arrival_price": "inklusive", "departure_price": "inklusive", "max_rental_period": "14", "fee_after_max": "5,95", "cancellation_fee": "Zone 1: 120€, Zone 2: 145€, Zone 3: 205€, Zone 4: 240€", "URL": "https://ravos.de/produkt/container-gruenschnitt/"},
{"source": "RAVOS Containerdienst", "title": "Holz A1-A3 3 m³", "type": "Holz A1-A3", "city": "Köln", "size": "3", "price": "199,00", "lid_price": null, "arrival_price": "inklusive", "departure_price": "inklusive", "max_rental_period": "14", "fee_after_max": "5,95", "cancellation_fee": "Zone 1: 120€, Zone 2: 145€, Zone 3: 205€, Zone 4: 240€", "URL": "https://ravos.de/produkt/container-holzabfall/"},
{"source": "RAVOS Containerdienst", "title": "Holz A1-A3 5 m³", "type": "Holz A1-A3", "city": "Köln", "size": "5", "price": "299,00", "lid_price": null, "arrival_price": "inklusive", "departure_price": "inklusive", "max_rental_period": "14", "fee_after_max": "5,95", "cancellation_fee": "Zone 1: 120€, Zone 2: 145€, Zone 3: 205€, Zone 4: 240€", "URL": "https://ravos.de/produkt/container-holzabfall/"},
{"source": "RAVOS Containerdienst", "title": "Holz A1-A3 7 m³", "type": "Holz A1-A3", "city": "Köln", "size": "7", "price": "369,00", "lid_price": null, "arrival_price": "inklusive", "departure_price": "inklusive", "max_rental_period": "14", "fee_after_max": "5,95", "cancellation_fee": "Zone 1: 120€, Zone 2: 145€, Zone 3: 205€, Zone 4: 240€", "URL": "https://ravos.de/produkt/container-holzabfall/"},
{"source": "RAVOS Containerdienst", "title": "Holz A1-A3 10 m³", "type": "Holz A1-A3", "city": "Köln", "size": "10", "price": "429,00", "lid_price": null, "arrival_price": "inklusive", "departure_price": "inklusive", "max_rental_period": "14", "fee_after_max": "5,95", "cancellation_fee": "Zone 1: 120€, Zone 2: 145€, Zone 3: 205€, Zone 4: 240€", "URL": "https://ravos.de/produkt/container-holzabfall/"},
{"source": "RAVOS Containerdienst", "title": "Boden 3 m³", "type": "Boden", "city": "Köln", "size": "3", "price": "269,00", "lid_price": null, "arrival_price": "inklusive", "departure_price": "inklusive", "max_rental_period": "14", "fee_after_max": "5,95", "cancellation_fee": "Zone 1: 120€, Zone 2: 145€, Zone 3: 205€, Zone 4: 240€", "URL": "https://ravos.de/produkt/container-erdaushub/"},
{"source": "RAVOS Containerdienst", "title": "Boden 5 m³", "type": "Boden", "city": "Köln", "size": "5", "price": "369,00", "lid_price": null, "arrival_price": "inklusive", "departure_price": "inklusive", "max_rental_period": "14", "fee_after_max": "5,95", "cancellation_fee": "Zone 1: 120€, Zone 2: 145€, Zone 3: 205€, Zone 4: 240€", "URL": "https://ravos.de/produkt/container-erdaushub/"},
{"source": "RAVOS Containerdienst", "title": "Boden 7 m³", "type": "Boden", "city": "Köln", "size": "7", "price": "429,00", "lid_price": null, "arrival_price": "inklusive", "departure_price": "inklusive", "max_rental_period": "14", "fee_after_max": "5,95", "cancellation_fee": "Zone 1: 120€, Zone 2: 145€, Zone 3: 205€, Zone 4: 240€", "URL": "https://ravos.de/produkt/container-erdaushub/"}
]